hypercomplex/__init__.py
hypercomplex/examples.py
hypercomplex/hypercomplex.py
hypercomplex/test_hypercomplex.py
hypercomplex-0.3.4.dist-info/LICENSE.txt
hypercomplex-0.3.4.dist-info/METADATA
hypercomplex-0.3.4.dist-info/WHEEL
hypercomplex-0.3.4.dist-info/top_level.txt
hypercomplex-0.3.4.dist-info/RECORD
