Metadata-Version: 2.1
Name: hypercomplex
Version: 0.3.4
Summary: Library for arbitrary-dimension hypercomplex numbers following the Cayley-Dickson construction.
Home-page: https://github.com/discretegames/hypercomplex
Author: discretegames
Author-email: discretizedgames@gmail.com
License: MIT
Project-URL: GitHub, https://github.com/discretegames/hypercomplex
Project-URL: PyPI, https://pypi.org/project/hypercomplex
Project-URL: TestPyPI, https://test.pypi.org/project/hypercomplex
Keywords: python,math,complex,number,hypercomplex,Cayley,Dickson,construction,algebra,quaternion,octonion,sedenion,pathion,chingon,routon,voudon
Platform: UNKNOWN
Classifier: Development Status :: 5 - Production/Stable
Classifier: Intended Audience :: Education
Classifier: Intended Audience :: Science/Research
Classifier: Topic :: Scientific/Engineering :: Mathematics
Classifier: License :: OSI Approved :: MIT License
Classifier: Programming Language :: Python :: 3
Classifier: Programming Language :: Python :: 3.6
Classifier: Programming Language :: Python :: 3.7
Classifier: Programming Language :: Python :: 3.8
Classifier: Programming Language :: Python :: 3.9
Classifier: Programming Language :: Python :: 3.10
Requires-Python: >=3.6
License-File: LICENSE.txt
Requires-Dist: mathdunders (>=0.4.1)
